archetypes.multilingual-3.0.9-py2.7-nspkg.pth
archetypes/multilingual/__init__.py
archetypes/multilingual/cloner.py
archetypes/multilingual/configure.zcml
archetypes/multilingual/interfaces.py
archetypes/multilingual/language.py
archetypes/multilingual/monkey.py
archetypes/multilingual/profile.zcml
archetypes/multilingual/rebuild_i18n.sh
archetypes/multilingual/setuphandlers.py
archetypes/multilingual/subscriber.py
archetypes/multilingual/testing.py
archetypes/multilingual/testing.zcml
archetypes/multilingual/utils.py
archetypes/multilingual/browser/__init__.py
archetypes/multilingual/browser/add.py
archetypes/multilingual/browser/at_babel_view.py
archetypes/multilingual/browser/configure.zcml
archetypes/multilingual/browser/translate.py
archetypes/multilingual/browser/viewlets.py
archetypes/multilingual/browser/templates/add-form-is-translation.pt
archetypes/multilingual/browser/templates/at_babel_view.pt
archetypes/multilingual/locales/archetypes.multilingual.pot
archetypes/multilingual/locales/ca/LC_MESSAGES/archetypes.multilingual.mo
archetypes/multilingual/locales/ca/LC_MESSAGES/archetypes.multilingual.po
archetypes/multilingual/locales/de/LC_MESSAGES/archetypes.multilingual.mo
archetypes/multilingual/locales/de/LC_MESSAGES/archetypes.multilingual.po
archetypes/multilingual/locales/es/LC_MESSAGES/archetypes.multilingual.mo
archetypes/multilingual/locales/es/LC_MESSAGES/archetypes.multilingual.po
archetypes/multilingual/locales/eu/LC_MESSAGES/archetypes.multilingual.mo
archetypes/multilingual/locales/eu/LC_MESSAGES/archetypes.multilingual.po
archetypes/multilingual/locales/fr/LC_MESSAGES/archetypes.multilingual.mo
archetypes/multilingual/locales/fr/LC_MESSAGES/archetypes.multilingual.po
archetypes/multilingual/profiles/default/browserlayer.xml
archetypes/multilingual/profiles/default/componentregistry.xml
archetypes/multilingual/profiles/default/metadata.xml
archetypes/multilingual/profiles/default/skins.xml
archetypes.multilingual-3.0.9.dist-info/METADATA
archetypes.multilingual-3.0.9.dist-info/WHEEL
archetypes.multilingual-3.0.9.dist-info/entry_points.txt
archetypes.multilingual-3.0.9.dist-info/namespace_packages.txt
archetypes.multilingual-3.0.9.dist-info/top_level.txt
archetypes.multilingual-3.0.9.dist-info/RECORD
