Metadata-Version: 2.1
Name: archetypes.multilingual
Version: 3.0.9
Summary: Multilingual support for archetypes.
Home-page: https://github.com/plone/archetypes.multilingual
Author: awello
Author-email: awello@gmail.com
License: GPL
Keywords: archetypes multilingual i18n translation
Platform: UNKNOWN
Classifier: Development Status :: 6 - Mature
Classifier: Framework :: Plone
Classifier: Framework :: Plone :: Addon
Classifier: Framework :: Plone :: 5.0
Classifier: Framework :: Plone :: 5.1
Classifier: Framework :: Plone :: 5.2
Classifier: License :: OSI Approved :: GNU General Public License (GPL)
Classifier: Programming Language :: Python
Classifier: Programming Language :: Python :: 2.7
Classifier: Programming Language :: Python :: 2 :: Only
Requires-Python: ==2.7.*
Requires-Dist: setuptools
Requires-Dist: Products.ATContentTypes
Requires-Dist: plone.app.multilingual
Requires-Dist: collective.monkeypatcher
Provides-Extra: test
Requires-Dist: plone.app.testing ; extra == 'test'
Requires-Dist: plone.app.multilingual[test] ; extra == 'test'
Requires-Dist: plone.app.contenttypes[archetypes] ; extra == 'test'
